seeingllama2/__init__.py
seeingllama2/__main__.py
seeingllama2/config/configuration.yaml
seeingllama2/config/prompt.txt
seeingllama2/main/__init__.py
seeingllama2/main/colors.py
seeingllama2/main/dialog_manager.py
seeingllama2/main/events.py
seeingllama2/main/interpreter.py
seeingllama2/main/routes.py
seeingllama2/main/utils.py
seeingllama2/main/voice.py
seeingllama2/main/large_language_models/__init__.py
seeingllama2/main/large_language_models/connectors.py
seeingllama2/main/large_language_models/oobabooga_connector.py
seeingllama2/static/css/app.css
seeingllama2/static/css/libs/bootstrap.min.css
seeingllama2/static/css/libs/entireframework.min.css
seeingllama2/static/img/favicon.svg
seeingllama2/static/img/logo.svg
seeingllama2/static/js/app.js
seeingllama2/static/js/package-lock.json
seeingllama2/static/js/package.json
seeingllama2/static/js/libs/bootstrap.min.js
seeingllama2/static/js/libs/bootstrap.min.js.map
seeingllama2/static/js/libs/jquery-3.7.0.min.js
seeingllama2/static/js/libs/jquery-3.7.0.min.map
seeingllama2/static/js/libs/popper.min.js
seeingllama2/static/js/libs/popper.min.js.map
seeingllama2/static/js/libs/socket.io.js
seeingllama2/static/js/libs/socket.io.js.map
seeingllama2/templates/index.htm
seeingllama2-0.0.6.dist-info/LICENSE
seeingllama2-0.0.6.dist-info/METADATA
seeingllama2-0.0.6.dist-info/WHEEL
seeingllama2-0.0.6.dist-info/entry_points.txt
seeingllama2-0.0.6.dist-info/top_level.txt
seeingllama2-0.0.6.dist-info/RECORD
