Metadata-Version: 2.1
Name: seeingllama2
Version: 0.0.6
Summary: A Python interactive agent for visually impaired and blind individuals.
Home-page: https://www.amisdesaveugles.org/comingsoon/
Author: Vincent Stragier
Author-email: vincent.stragier@outlook.com
Project-URL: Bug Tracker, https://github.com/Vincent-Stragier/c-bot/
Classifier: License :: OSI Approved :: GNU General Public License v3 (GPLv3)
Classifier: Operating System :: OS Independent
Classifier: Programming Language :: Python :: 3
Requires-Python: <4,>=3.10
License-File: LICENSE
Requires-Dist: Flask ==2.2.5
Requires-Dist: Flask-SocketIO ==5.3.1
Requires-Dist: PyYAML ==6.0.1
Requires-Dist: eventlet ==0.33.3
Requires-Dist: pyttsx4 ==3.0.15
Requires-Dist: setuptools >=65.5.1
